{
  "id": "default_flow",
  "name": "AI Based",
  "trigger_keywords": [
    "hello",
    "hi",
    "start",
    "hey"
  ],
  "nodes": [
    {
      "id": "node_1",
      "message": "Hey boss! 👋\nAko si AutoBot ng 1625 Auto Lab.\n\nKamusta ka? Anong balita?\n\nPwede kitang tulungan sa:\n• Pag-book ng service\n• Pag-check ng available services\n• Info tungkol sa shop\n\nSabihin mo lang, hal. 'anong services nyo', 'book ako', o 'saan location nyo?'\n\nKwentuhan muna tayo kung gusto mo! 😄",
      "input_type": "text",
      "variable": "last_user_input",
      "validation": null,
      "options": [
        {"label": "Tingnan ang Services", "value": "services", "next": "node_services"},
        {"label": "Book Now", "value": "book", "next": "node_services"},
        {"label": "Shop Info", "value": "info", "next": "node_shop_info"}
      ],
      "next": "node_ai_processing",
      "http_request": null,
      "normalize_skip": false,
      "payload_assign": null
    },
    {
      "id": "node_ai_processing",
      "message": "",
      "input_type": "none",
      "validation": null,
      "options": [],
      "next": "node_ai_router",
      "http_request": {
        "method": "POST",
        "url": "http://localhost:8300/ai/evaluate",
        "headers": {
          "Content-Type": "application/json"
        },
        "body": {
          "user_message": "{last_user_input}",
          "kb_context": "{admin_kb_text}"
        },
        "response_variable": "ai_response_object"
      },
      "normalize_skip": false,
      "payload_assign": {
        "ai_reply": [
          "ai_response_object.message"
        ],
        "ai_intent": [
          "ai_response_object.suggested_action"
        ]
      }
    },
    {
      "id": "node_ai_router",
      "message": "{ai_reply}\n\nMay gusto ka pa bang itanong, boss? Kung may follow-up ka, go lang! 👂",
      "input_type": "none",
      "validation": null,
      "options": [],
      "next": "node_ai_fallback",
      "http_request": null,
      "normalize_skip": false,
      "payload_assign": null,
      "routing_rules": [
        {"condition": "{ai_intent} == 'services'", "next": "node_services"},
        {"condition": "{ai_intent} == 'book'", "next": "node_services"},
        {"condition": "{ai_intent} == 'location'", "next": "node_shop_info"},
        {"condition": "{ai_intent} == 'info'", "next": "node_shop_info"},
        {"condition": "{ai_intent} == 'fallback'", "next": "node_ai_fallback"}
      ]
    },
    {
      "id": "node_ai_fallback",
      "message": "Ay, sorry boss, parang di ko masyadong nakuha. 😅\n\nBaka puyat lang ako! Pwede mo bang i-rephrase o pumili sa menu sa ibaba?\n\nKung gusto mo rin magkwento o magtanong ng kahit ano, game ako!",
      "input_type": "quick_reply",
      "options": [
        {"label": "Tingnan ang Services", "value": "services", "next": "node_services"},
        {"label": "Book Now", "value": "book", "next": "node_services"},
        {"label": "Shop Info", "value": "info", "next": "node_shop_info"}
      ],
      "next": "node_ai_idle"
    },
    {
      "id": "node_shop_info",
      "message": "Nasa Quezon City kami, boss! Metro Manila represent. 🚗\n\nOpen kami Mon–Sat, 9am–6pm.\n\nMay gusto ka pa bang malaman o itanong? Huwag mahiyang magtanong, parang tropa lang tayo dito!",
      "input_type": "quick_reply",
      "options": [
        {"label": "Tingnan ang Services", "value": "services", "next": "node_services"},
        {"label": "Book Now", "value": "book", "next": "node_services"},
        {"label": "Wala na, salamat!", "value": "end", "next": "node_ai_idle"}
      ],
      "next": "node_ai_idle"
    },
    {
      "id": "node_ai_idle",
      "message": "",
      "input_type": "text",
      "variable": "last_user_input",
      "validation": null,
      "options": [],
      "next": "node_ai_processing",
      "http_request": null,
      "normalize_skip": false,
      "payload_assign": null
    },
    {
      "id": "node_services",
      "message": "Eto ang mga services na pwede naming gawin para sa'yo, boss! Pili ka lang o itanong mo kung curious ka sa details. Kung gusto mo ng recommendation, sabihin mo lang anong trip mo sa kotse mo!",
      "input_type": "none",
      "validation": null,
      "options": [],
      "next": "node_choose_service",
      "http_request": {
        "method": "GET",
        "url": "http://localhost:8000/api/manychat/menu",
        "response_variable": "services",
        "render_cards": true
      },
      "normalize_skip": false,
      "payload_assign": null
    },
    {
      "id": "node_choose_service",
      "message": "Pindot ka lang ng service card sa taas, o i-type mo kung may specific kang gusto. Kung di ka sure, tanong ka lang—walang mali sa magtanong!",
      "input_type": "text",
      "variable": "service_id",
      "validation": {
        "type": "number",
        "error_message": "Boss, pili ka sa service cards sa taas o maglagay ng valid service ID."
      },
      "options": [],
      "next": "node_variants",
      "http_request": null,
      "normalize_skip": false,
      "payload_assign": {
        "service_id": [
          "service_id",
          "serviceId"
        ],
        "service_name": [
          "service_name",
          "serviceName",
          "title"
        ]
      }
    },
    {
      "id": "node_variants",
      "message": "Boss, eto ang mga variants na pwede mong pagpilian para sa service na yan. Kung gusto mo ng tips o may tanong ka, sabihin mo lang!",
      "input_type": "none",
      "validation": null,
      "options": [],
      "next": "node_select_variant",
      "http_request": {
        "method": "POST",
        "url": "http://localhost:8000/api/manychat/variants",
        "headers": {
          "Content-Type": "application/json"
        },
        "body": {
          "service_id": {
            "$int": "{service_id}"
          }
        },
        "response_variable": "variants",
        "next_if_empty": "node_no_slots",
        "render_cards": true
      },
      "normalize_skip": false,
      "payload_assign": null
    },
    {
      "id": "node_select_variant",
      "message": "Pindot ka lang ng variant card sa taas, o i-type mo kung may specific kang gusto. Kung di ka sigurado, itanong mo lang—walang judgment dito!",
      "input_type": "text",
      "variable": "variant_id",
      "validation": {
        "type": "number",
        "error_message": "Boss, pili ka sa variant cards sa taas o maglagay ng valid variant ID."
      },
      "options": [],
      "next": "node_book_prompt",
      "http_request": null,
      "normalize_skip": false,
      "payload_assign": {
        "variant_id": [
          "variant_id",
          "variationId"
        ],
        "variation_name": [
          "variationName",
          "variant_name",
          "title"
        ],
        "variation_details": [
          "subtitle",
          "variation_details"
        ],
        "variation_specs": [
          "specs_summary",
          "variation_specs"
        ]
      }
    },
    {
      "id": "node_book_prompt",
      "message": "Game na ba, boss?\n\n'{variation_name}' ang napili mo.\n{variation_details}\n\nKung ready ka na, pindot lang. Kung may tanong ka pa, wag mahiyang magtanong!",
      "input_type": "quick_reply",
      "validation": null,
      "options": [
        {
          "label": "Yes, book now",
          "value": "yes",
          "next": "node_name"
        },
        {
          "label": "Talk to Human",
          "value": "human",
          "next": "handoff"
        },
        {
          "label": "Back to Menu",
          "value": "menu",
          "next": "node_start"
        }
      ],
      "next": null,
      "http_request": null,
      "normalize_skip": false,
      "payload_assign": null
    },
    {
      "id": "node_name",
      "message": "Solid! Pahingi ng full name mo, boss, para maayos natin ang booking mo. Promise, di ko ipopost sa FB! 😁",
      "input_type": "text",
      "variable": "name",
      "validation": {
        "type": "required"
      },
      "options": [],
      "next": "node_email",
      "http_request": null,
      "normalize_skip": false,
      "payload_assign": null
    },
    {
      "id": "node_email",
      "message": "Email address mo, boss? Para ma-confirm ko ang booking at ma-update ka agad. Hindi ako mag-spam, scout's honor!",
      "input_type": "text",
      "variable": "email",
      "validation": {
        "type": "email",
        "error_message": "Boss, invalid email 'yan. Check mo uli."
      },
      "options": [],
      "next": "node_phone",
      "http_request": null,
      "normalize_skip": false,
      "payload_assign": null
    },
    {
      "id": "node_phone",
      "message": "Contact number mo, boss? (Promise, di kita tatawagan ng 3am 😂) Kung gusto mo Viber o WhatsApp, sabihin mo rin!",
      "input_type": "text",
      "variable": "phone",
      "validation": {
        "type": "regex",
        "pattern": "^(?:\\+63|0)?9\\d{9}$",
        "error_message": "Boss, valid PH mobile number lang (e.g., 09171234567 or +639171234567)."
      },
      "options": [],
      "next": "node_vehicle_make",
      "http_request": null,
      "normalize_skip": false,
      "payload_assign": null
    },
    {
      "id": "node_vehicle_make",
      "message": "Anong make ng sasakyan mo, boss? (hal. Honda, Toyota, BMW) Kung may kwento ka sa kotse mo, share mo rin!",
      "input_type": "text",
      "variable": "vehicle_make",
      "validation": {
        "type": "required"
      },
      "options": [],
      "next": "node_vehicle_model",
      "http_request": null,
      "normalize_skip": false,
      "payload_assign": null
    },
    {
      "id": "node_vehicle_model",
      "message": "Model ng sasakyan mo? (hal. Civic, Camry, M340i) Curious ako kung anong ride mo!",
      "input_type": "text",
      "variable": "vehicle_model",
      "validation": {
        "type": "required"
      },
      "options": [],
      "next": "node_vehicle_year",
      "http_request": null,
      "normalize_skip": false,
      "payload_assign": null
    },
    {
      "id": "node_vehicle_year",
      "message": "Anong year ng sasakyan mo, boss? (1980-2027 lang) Classic ba o bago?",
      "input_type": "text",
      "variable": "vehicle_year",
      "validation": {
        "type": "year_range",
        "min": 1980,
        "max": 2027,
        "error_message": "Boss, invalid vehicle year. 1980 hanggang 2027 lang valid."
      },
      "options": [],
      "next": "node_date",
      "http_request": null,
      "normalize_skip": false,
      "payload_assign": null
    },
    {
      "id": "node_date",
      "message": "Kailan mo gusto magpa-book, boss? Pwede YYYY-MM-DD, 'bukas', o 'next week'. Kung may special request ka sa date, sabihin mo lang!",
      "input_type": "text",
      "variable": "appointment_date",
      "validation": {
        "type": "date"
      },
      "options": [],
      "next": "node_availability",
      "http_request": null,
      "normalize_skip": false,
      "payload_assign": null
    },
    {
      "id": "node_availability",
      "message": "Eto ang mga available na oras para sa {appointment_date}, boss. Pili ka lang o itanong mo kung may concern ka. Kung gusto mo ng coffee habang naghihintay, libre yan! ☕",
      "input_type": "none",
      "validation": null,
      "options": [],
      "next": "node_time",
      "http_request": {
        "method": "GET",
        "url": "http://localhost:8000/api/bookings/availability?date={appointment_date}",
        "response_variable": "available_slots",
        "response_field": "availableSlots",
        "next_if_empty": "node_no_slots",
        "render_quick_replies": true
      },
      "normalize_skip": false,
      "payload_assign": null
    },
    {
      "id": "node_no_slots",
      "message": "Ay, sorry boss, puno na kami sa date na 'yan. 😔\n\nPili ka ng ibang araw o itanong mo kung may special request ka. Baka may ma-suggest akong alternative!",
      "input_type": "quick_reply",
      "validation": null,
      "options": [
        {
          "label": "Oo, ibang date",
          "value": "yes",
          "next": "node_date"
        },
        {
          "label": "Talk to Human",
          "value": "human",
          "next": "handoff"
        }
      ],
      "next": null,
      "http_request": null,
      "normalize_skip": false,
      "payload_assign": null
    },
    {
      "id": "node_time",
      "message": "Pili ka ng oras sa taas o i-type mo exact (hal. 10:00 AM). Kung may preferred time ka, sabihin mo lang—flexible kami!",
      "input_type": "text",
      "variable": "appointment_time",
      "validation": {
        "type": "in_list_variable",
        "list_variable": "available_slots",
        "error_message": "Boss, pili ka lang ng time slot na nasa options sa taas."
      },
      "options": [],
      "next": "node_notes",
      "http_request": null,
      "normalize_skip": false,
      "payload_assign": null
    },
    {
      "id": "node_notes",
      "message": "May gusto ka bang idagdag na notes, boss? Type 'skip' kung wala na.\n\nKahit kwento lang, okay lang! Mahilig din ako makinig ng car stories.",
      "input_type": "text",
      "variable": "notes",
      "validation": null,
      "options": [],
      "next": "node_images",
      "http_request": null,
      "normalize_skip": true,
      "payload_assign": null
    },
    {
      "id": "node_images",
      "message": "Kung may photos ka ng sasakyan, upload mo dito gamit ang 📎. Type 'skip' kung wala.\n\nMas madali naming ma-assess kung may pics! Gusto mo, pwede mo rin i-share best angle ng ride mo!",
      "input_type": "text",
      "variable": "images_input",
      "validation": null,
      "options": [],
      "next": "node_confirm_summary",
      "http_request": null,
      "normalize_skip": true,
      "payload_assign": null
    },
    {
      "id": "node_confirm_summary",
      "message": "Boss, pacheck kung tama ang details:\n🚗 {vehicle_year} {vehicle_make} {vehicle_model}\n🛠 Service: {service_name} ({variation_name})\n📅 Sched: {appointment_date} @ {appointment_time}\n\nTama ba lahat? Kung may gusto kang baguhin, sabihin mo lang—walang problema!",
      "input_type": "quick_reply",
      "validation": null,
      "options": [
        {
          "label": "G! Send na.",
          "value": "confirm",
          "next": "node_submit_booking"
        },
        {
          "label": "Wait, may babaguhin ako.",
          "value": "edit",
          "next": "node_edit_menu"
        }
      ],
      "next": null,
      "http_request": null,
      "normalize_skip": false,
      "payload_assign": null
    },
    {
      "id": "node_edit_menu",
      "message": "Ano gusto mong baguhin, boss?",
      "input_type": "quick_reply",
      "validation": null,
      "options": [
        {
          "label": "Service/Variant",
          "value": "edit_service",
          "next": "node_edit_services"
        },
        {
          "label": "Date/Time",
          "value": "edit_schedule",
          "next": "node_edit_date"
        },
        {
          "label": "Contact Details",
          "value": "edit_contact",
          "next": "node_edit_name"
        },
        {
          "label": "Notes/Images",
          "value": "edit_notes",
          "next": "node_edit_notes"
        },
        {
          "label": "Back to Summary",
          "value": "back",
          "next": "node_confirm_summary"
        }
      ],
      "next": null,
      "http_request": null,
      "normalize_skip": false,
      "payload_assign": null
    },
    {
      "id": "node_edit_services",
      "message": "Sige boss, pili ulit tayo ng service:",
      "input_type": "none",
      "validation": null,
      "options": [],
      "next": "node_edit_choose_service",
      "http_request": {
        "method": "GET",
        "url": "http://localhost:8000/api/manychat/menu",
        "response_variable": "services",
        "render_cards": true
      },
      "normalize_skip": false,
      "payload_assign": null
    },
    {
      "id": "node_edit_choose_service",
      "message": "Pili ka ng bagong service card sa taas.",
      "input_type": "text",
      "variable": "service_id",
      "validation": {
        "type": "number",
        "error_message": "Boss, pili ka sa service cards sa taas o maglagay ng valid service ID."
      },
      "options": [],
      "next": "node_edit_variants",
      "http_request": null,
      "normalize_skip": false,
      "payload_assign": {
        "service_id": [
          "service_id",
          "serviceId"
        ],
        "service_name": [
          "service_name",
          "serviceName",
          "title"
        ]
      }
    },
    {
      "id": "node_edit_variants",
      "message": "Eto mga available variants:",
      "input_type": "none",
      "validation": null,
      "options": [],
      "next": "node_edit_select_variant",
      "http_request": {
        "method": "POST",
        "url": "http://localhost:8000/api/manychat/variants",
        "headers": {
          "Content-Type": "application/json"
        },
        "body": {
          "service_id": {
            "$int": "{service_id}"
          }
        },
        "response_variable": "variants",
        "next_if_empty": "node_no_slots",
        "render_cards": true
      },
      "normalize_skip": false,
      "payload_assign": null
    },
    {
      "id": "node_edit_select_variant",
      "message": "Pili ka ng bagong variant card sa taas.",
      "input_type": "text",
      "variable": "variant_id",
      "validation": {
        "type": "number",
        "error_message": "Boss, pili ka sa variant cards sa taas o maglagay ng valid variant ID."
      },
      "options": [],
      "next": "node_confirm_summary",
      "http_request": null,
      "normalize_skip": false,
      "payload_assign": {
        "variant_id": [
          "variant_id",
          "variationId"
        ],
        "variation_name": [
          "variationName",
          "variant_name",
          "title"
        ]
      }
    },
    {
      "id": "node_edit_date",
      "message": "Kailan bagong booking date? Pwede YYYY-MM-DD, 'bukas', o 'next week'.",
      "input_type": "text",
      "variable": "appointment_date",
      "validation": {
        "type": "date"
      },
      "options": [],
      "next": "node_edit_availability",
      "http_request": null,
      "normalize_skip": false,
      "payload_assign": null
    },
    {
      "id": "node_edit_availability",
      "message": "Eto available times para sa {appointment_date}:",
      "input_type": "none",
      "validation": null,
      "options": [],
      "next": "node_edit_time",
      "http_request": {
        "method": "GET",
        "url": "http://localhost:8000/api/bookings/availability?date={appointment_date}",
        "response_variable": "available_slots",
        "response_field": "availableSlots",
        "next_if_empty": "node_no_slots",
        "render_quick_replies": true
      },
      "normalize_skip": false,
      "payload_assign": null
    },
    {
      "id": "node_edit_time",
      "message": "Pili ka ng bagong oras sa taas o i-type mo exact.",
      "input_type": "text",
      "variable": "appointment_time",
      "validation": {
        "type": "in_list_variable",
        "list_variable": "available_slots",
        "error_message": "Boss, pili ka lang ng time slot na nasa options sa taas."
      },
      "options": [],
      "next": "node_confirm_summary",
      "http_request": null,
      "normalize_skip": false,
      "payload_assign": null
    },
    {
      "id": "node_edit_name",
      "message": "Anong tamang full name mo, boss?",
      "input_type": "text",
      "variable": "name",
      "validation": {
        "type": "required"
      },
      "options": [],
      "next": "node_edit_email",
      "http_request": null,
      "normalize_skip": false,
      "payload_assign": null
    },
    {
      "id": "node_edit_email",
      "message": "Anong tamang email mo?",
      "input_type": "text",
      "variable": "email",
      "validation": {
        "type": "email",
        "error_message": "Boss, invalid email 'yan. Check mo uli."
      },
      "options": [],
      "next": "node_edit_phone",
      "http_request": null,
      "normalize_skip": false,
      "payload_assign": null
    },
    {
      "id": "node_edit_phone",
      "message": "Anong tamang phone number mo?",
      "input_type": "text",
      "variable": "phone",
      "validation": {
        "type": "regex",
        "pattern": "^(?:\\+63|0)?9\\d{9}$",
        "error_message": "Boss, valid PH mobile number lang (e.g., 09171234567 or +639171234567)."
      },
      "options": [],
      "next": "node_confirm_summary",
      "http_request": null,
      "normalize_skip": false,
      "payload_assign": null
    },
    {
      "id": "node_edit_notes",
      "message": "Updated notes? Type skip kung wala.",
      "input_type": "text",
      "variable": "notes",
      "validation": null,
      "options": [],
      "next": "node_edit_images",
      "http_request": null,
      "normalize_skip": true,
      "payload_assign": null
    },
    {
      "id": "node_edit_images",
      "message": "Updated image URL(s), comma-separated. Type skip kung wala.",
      "input_type": "text",
      "variable": "images_input",
      "validation": null,
      "options": [],
      "next": "node_confirm_summary",
      "http_request": null,
      "normalize_skip": true,
      "payload_assign": null
    },
    {
      "id": "node_submit_booking",
      "message": "Sige boss, isusubmit ko na booking request mo...\n\nHintay lang ng konti, tapos update kita agad! Excited na ako makita ang ride mo!",
      "input_type": "none",
      "validation": null,
      "options": [],
      "next": "node_booking_done",
      "http_request": {
        "method": "POST",
        "url": "http://localhost:8000/api/booking/external",
        "headers": {
          "Content-Type": "application/json"
        },
        "body": {
          "source": "chatbot",
          "name": "{name}",
          "email": "{email}",
          "phone": "{phone}",
          "vehicleInfo": "{vehicle_make} {vehicle_model} {vehicle_year}",
          "vehicleMake": "{vehicle_make}",
          "vehicleModel": "{vehicle_model}",
          "vehicleYear": "{vehicle_year}",
          "serviceId": {
            "$int": "{service_id}"
          },
          "selectedVariations": {
            "$variations": {
              "serviceId": "{service_id}",
              "variationId": "{variant_id}",
              "variationName": "{variation_name}"
            }
          },
          "appointmentDate": "{appointment_date}",
          "appointmentTime": "{appointment_time}",
          "notes": "{notes}",
          "mediaUrls": {
            "$csv": "{images_input}"
          }
        },
        "response_variable": "booking_result"
      },
      "normalize_skip": false,
      "payload_assign": null
    },
    {
      "id": "node_booking_done",
      "message": "✅ Ayos! Submitted na booking mo, boss.\n\nKung may gusto ka pang ipa-assist, itanong, o magkwento lang, nandito lang ako! Salamat sa tiwala!",
      "input_type": "quick_reply",
      "validation": null,
      "options": [
        {
          "label": "View Services",
          "value": "services",
          "next": "node_services"
        },
        {
          "label": "Talk to Human",
          "value": "human",
          "next": "handoff"
        },
        {
          "label": "Done",
          "value": "done",
          "next": "node_start"
        }
      ],
      "next": null,
      "http_request": null,
      "normalize_skip": false,
      "payload_assign": null
    },
    {
      "id": "node_start",
      "message": "Ano pa ang pwede kong gawin para sa'yo, boss? Usap pa tayo! O kung gusto mo mag-share ng car tips, game ako!",
      "input_type": "text",
      "variable": "last_user_input",
      "validation": null,
      "options": [],
      "next": "node_ai_processing",
      "http_request": null,
      "normalize_skip": false,
      "payload_assign": null
    }
  ]
}